{
  "date": "2026-04-01",
  "generated_at": "2026-04-01T13:01:19.233994+00:00",
  "regressions_detected": 0,
  "total_checks": 6,
  "results": [
    {
      "bug_id": "explore-empty",
      "detected": false,
      "details": null
    },
    {
      "bug_id": "paywalled-explore",
      "detected": false,
      "details": null
    },
    {
      "bug_id": "nba-score-formatting",
      "detected": true,
      "details": null
    },
    {
      "bug_id": "cross-section-bleed",
      "detected": false,
      "details": null
    },
    {
      "bug_id": "cross-section-duplicate",
      "detected": false,
      "details": null
    },
    {
      "bug_id": "vague-hallucinated-sources",
      "detected": false,
      "details": null
    }
  ]
}